bugbuzz/__init__.py
bugbuzz/packages/__init__.py
bugbuzz/packages/pubnub/__init__.py
bugbuzz/packages/pubnub/LICENSE
bugbuzz/packages/requests/__init__.py
bugbuzz/packages/requests/adapters.py
bugbuzz/packages/requests/api.py
bugbuzz/packages/requests/auth.py
bugbuzz/packages/requests/cacert.pem
bugbuzz/packages/requests/certs.py
bugbuzz/packages/requests/compat.py
bugbuzz/packages/requests/cookies.py
bugbuzz/packages/requests/exceptions.py
bugbuzz/packages/requests/hooks.py
bugbuzz/packages/requests/models.py
bugbuzz/packages/requests/sessions.py
bugbuzz/packages/requests/status_codes.py
bugbuzz/packages/requests/structures.py
bugbuzz/packages/requests/utils.py
bugbuzz/packages/requests/packages/__init__.py
bugbuzz/packages/requests/packages/chardet/__init__.py
bugbuzz/packages/requests/packages/chardet/big5freq.py
bugbuzz/packages/requests/packages/chardet/big5prober.py
bugbuzz/packages/requests/packages/chardet/chardetect.py
bugbuzz/packages/requests/packages/chardet/chardistribution.py
bugbuzz/packages/requests/packages/chardet/charsetgroupprober.py
bugbuzz/packages/requests/packages/chardet/charsetprober.py
bugbuzz/packages/requests/packages/chardet/codingstatemachine.py
bugbuzz/packages/requests/packages/chardet/compat.py
bugbuzz/packages/requests/packages/chardet/constants.py
bugbuzz/packages/requests/packages/chardet/cp949prober.py
bugbuzz/packages/requests/packages/chardet/escprober.py
bugbuzz/packages/requests/packages/chardet/escsm.py
bugbuzz/packages/requests/packages/chardet/eucjpprober.py
bugbuzz/packages/requests/packages/chardet/euckrfreq.py
bugbuzz/packages/requests/packages/chardet/euckrprober.py
bugbuzz/packages/requests/packages/chardet/euctwfreq.py
bugbuzz/packages/requests/packages/chardet/euctwprober.py
bugbuzz/packages/requests/packages/chardet/gb2312freq.py
bugbuzz/packages/requests/packages/chardet/gb2312prober.py
bugbuzz/packages/requests/packages/chardet/hebrewprober.py
bugbuzz-0.1.2.dist-info/DESCRIPTION.rst
bugbuzz-0.1.2.dist-info/METADATA
bugbuzz-0.1.2.dist-info/metadata.json
bugbuzz-0.1.2.dist-info/RECORD
bugbuzz-0.1.2.dist-info/top_level.txt
bugbuzz-0.1.2.dist-info/WHEEL
